[{"page":186,"sura":8,"ayat":70,"html":"<!DOCTYPE html >\r\n<html lang=\"en\">\r\n<head>\r\n<meta http-equiv=\"X-UA-Compatible\" content=\"IE=Edge\" />\r\n<meta charset=\"utf-8\" />\r\n</head>\r\n\r\n<body style=\"\">\r\n<div class=\"quran-container\">\r\n<!-- Begin shared CSS values -->\r\n<style id=\"classes\" type=\"text/css\" >\r\n    .quran-container {\r\n        width: 520px;\r\n        text-align: right;\r\n        padding: 10px;\r\n        margin: 0 auto;\r\n    }\r\n    .ayat-text {\r\n        \r\n    }\r\n    .sura-name {\r\n        text-align: center;\r\n    }\r\n    .line {\r\n    }\r\n.fontQCF_P186 { font-size:36px;font-family:QCF_P186;color:#000;}.ayat8_70 {}\n.ayat8_71 {}\n.line { text-align: center; }.ayat-text {  }.ayat-text:hover { color: #08e8de !important; cursor: pointer; cursor: pointer !important; }.invisible-text { color: white !important;\r\n                            -moz-user-select: none;\r\n                            -webkit-user-select: none;\r\n                            -ms-user-select: none;\r\n                            user-select: none;\r\n                            -o-user-select: none;}.invisible-text:hover { color: white !important;\r\n                            cursor: default !important;\r\n                            -moz-user-select: none;\r\n                            -webkit-user-select: none;\r\n                            -ms-user-select: none;\r\n                            user-select: none;\r\n                            -o-user-select: none;}\r\n</style>\r\n<!-- End inline CSS -->\r\n\r\n<!-- Begin embedded font definitions -->\r\n<style id=\"fonts1\" type=\"text/css\" >\r\n@font-face {font-family: QCF_P186; src: url(\"https://imanakhov.github.io/fonts/qcf_p186.ttf\") format(\"opentype\");}\r\n</style>\r\n<!-- End embedded font definitions -->\r\n\r\n<!-- Begin text definitions (Positioned/styled in CSS) -->\r\n<div class=\"page\"><div class=\"line\"><span class=\"fontQCF_P186 ayat-text sura8 ayat8_70\">ﭑ</span><span class=\"fontQCF_P186 ayat-text sura8 ayat8_70\">ﭒ</span><span class=\"fontQCF_P186 ayat-text sura8 ayat8_70\">ﭓ</span><span class=\"fontQCF_P186 ayat-text sura8 ayat8_70\">ﭔ</span><span class=\"fontQCF_P186 ayat-text sura8 ayat8_70\">ﭕ</span><span class=\"fontQCF_P186 ayat-text sura8 ayat8_70\">ﭖ</span><span class=\"fontQCF_P186 ayat-text sura8 ayat8_70\">ﭗ</span><span class=\"fontQCF_P186 ayat-text sura8 ayat8_70\">ﭘ</span><span class=\"fontQCF_P186 ayat-text sura8 ayat8_70\">ﭙ</span><span class=\"fontQCF_P186 ayat-text sura8 ayat8_70\">ﭚ</span><span class=\"fontQCF_P186 ayat-text sura8 ayat8_70\">ﭛ</span></div><div class=\"line\"><span class=\"fontQCF_P186 ayat-text sura8 ayat8_70\">ﭜ</span><span class=\"fontQCF_P186 ayat-text sura8 ayat8_70\">ﭝ</span><span class=\"fontQCF_P186 ayat-text sura8 ayat8_70\">ﭞ</span><span class=\"fontQCF_P186 ayat-text sura8 ayat8_70\">ﭟ</span><span class=\"fontQCF_P186 ayat-text sura8 ayat8_70\">ﭠ</span><span class=\"fontQCF_P186 ayat-text sura8 ayat8_70\">ﭡ</span><span class=\"fontQCF_P186 ayat-text sura8 ayat8_70\">ﭢ</span><span class=\"fontQCF_P186 ayat-text sura8 ayat8_70\">ﭣ</span><span class=\"fontQCF_P186 ayat-text sura8 ayat8_70\">ﭤ</span><span class=\"fontQCF_P186 ayat-text sura8 ayat8_70\">ﭥ</span><span class=\"fontQCF_P186 ayat-text sura8 ayat8_70\">ﭦ</span></div><div class=\"line\"><span class=\"fontQCF_P186 ayat-text sura8 ayat8_70\">ﭧ</span><span class=\"fontQCF_P186 ayat-text sura8 ayat8_70\">ﭨ</span><span class=\"fontQCF_P186 ayat-text sura8 ayat8_70\">ﭩ</span><span class=\"fontQCF_P186 ayat-text sura8 ayat8_70\">ﭪ</span><span class=\"fontQCF_P186 ayat-text invisible-text sura8 ayat8_71\">ﭫ</span><span class=\"fontQCF_P186 ayat-text invisible-text sura8 ayat8_71\">ﭬ</span><span class=\"fontQCF_P186 ayat-text invisible-text sura8 ayat8_71\">ﭭ</span><span class=\"fontQCF_P186 ayat-text invisible-text sura8 ayat8_71\">ﭮ</span><span class=\"fontQCF_P186 ayat-text invisible-text sura8 ayat8_71\">ﭯ</span></div></div>\r\n<!-- End text definitions -->\r\n</div>\r\n</body>\r\n</html>\r\n"},{"page":186,"sura":8,"ayat":71,"html":"<!DOCTYPE html >\r\n<html lang=\"en\">\r\n<head>\r\n<meta http-equiv=\"X-UA-Compatible\" content=\"IE=Edge\" />\r\n<meta charset=\"utf-8\" />\r\n</head>\r\n\r\n<body style=\"\">\r\n<div class=\"quran-container\">\r\n<!-- Begin shared CSS values -->\r\n<style id=\"classes\" type=\"text/css\" >\r\n    .quran-container {\r\n        width: 520px;\r\n        text-align: right;\r\n        padding: 10px;\r\n        margin: 0 auto;\r\n    }\r\n    .ayat-text {\r\n        \r\n    }\r\n    .sura-name {\r\n        text-align: center;\r\n    }\r\n    .line {\r\n    }\r\n.fontQCF_P186 { font-size:36px;font-family:QCF_P186;color:#000;}.ayat8_70 {}\n.ayat8_71 {}\n.ayat8_72 {}\n.line { text-align: center; }.ayat-text {  }.ayat-text:hover { color: #08e8de !important; cursor: pointer; cursor: pointer !important; }.invisible-text { color: white !important;\r\n                            -moz-user-select: none;\r\n                            -webkit-user-select: none;\r\n                            -ms-user-select: none;\r\n                            user-select: none;\r\n                            -o-user-select: none;}.invisible-text:hover { color: white !important;\r\n                            cursor: default !important;\r\n                            -moz-user-select: none;\r\n                            -webkit-user-select: none;\r\n                            -ms-user-select: none;\r\n                            user-select: none;\r\n                            -o-user-select: none;}\r\n</style>\r\n<!-- End inline CSS -->\r\n\r\n<!-- Begin embedded font definitions -->\r\n<style id=\"fonts1\" type=\"text/css\" >\r\n@font-face {font-family: QCF_P186; src: url(\"https://imanakhov.github.io/fonts/qcf_p186.ttf\") format(\"opentype\");}\r\n</style>\r\n<!-- End embedded font definitions -->\r\n\r\n<!-- Begin text definitions (Positioned/styled in CSS) -->\r\n<div class=\"page\"><div class=\"line\"><span class=\"fontQCF_P186 ayat-text invisible-text sura8 ayat8_70\">ﭧ</span><span class=\"fontQCF_P186 ayat-text invisible-text sura8 ayat8_70\">ﭨ</span><span class=\"fontQCF_P186 ayat-text invisible-text sura8 ayat8_70\">ﭩ</span><span class=\"fontQCF_P186 ayat-text invisible-text sura8 ayat8_70\">ﭪ</span><span class=\"fontQCF_P186 ayat-text sura8 ayat8_71\">ﭫ</span><span class=\"fontQCF_P186 ayat-text sura8 ayat8_71\">ﭬ</span><span class=\"fontQCF_P186 ayat-text sura8 ayat8_71\">ﭭ</span><span class=\"fontQCF_P186 ayat-text sura8 ayat8_71\">ﭮ</span><span class=\"fontQCF_P186 ayat-text sura8 ayat8_71\">ﭯ</span></div><div class=\"line\"><span class=\"fontQCF_P186 ayat-text sura8 ayat8_71\">ﭰ</span><span class=\"fontQCF_P186 ayat-text sura8 ayat8_71\">ﭱ</span><span class=\"fontQCF_P186 ayat-text sura8 ayat8_71\">ﭲ</span><span class=\"fontQCF_P186 ayat-text sura8 ayat8_71\">ﭳ</span><span class=\"fontQCF_P186 ayat-text sura8 ayat8_71\">ﭴ</span><span class=\"fontQCF_P186 ayat-text sura8 ayat8_71\">ﭵ</span><span class=\"fontQCF_P186 ayat-text sura8 ayat8_71\">ﭶ</span><span class=\"fontQCF_P186 ayat-text sura8 ayat8_71\">ﭷ</span><span class=\"fontQCF_P186 ayat-text sura8 ayat8_71\">ﭸ</span><span class=\"fontQCF_P186 ayat-text sura8 ayat8_71\">ﭹ</span><span class=\"fontQCF_P186 ayat-text invisible-text sura8 ayat8_72\">ﭺ</span><span class=\"fontQCF_P186 ayat-text invisible-text sura8 ayat8_72\">ﭻ</span></div></div>\r\n<!-- End text definitions -->\r\n</div>\r\n</body>\r\n</html>\r\n"},{"page":186,"sura":8,"ayat":72,"html":"<!DOCTYPE html >\r\n<html lang=\"en\">\r\n<head>\r\n<meta http-equiv=\"X-UA-Compatible\" content=\"IE=Edge\" />\r\n<meta charset=\"utf-8\" />\r\n</head>\r\n\r\n<body style=\"\">\r\n<div class=\"quran-container\">\r\n<!-- Begin shared CSS values -->\r\n<style id=\"classes\" type=\"text/css\" >\r\n    .quran-container {\r\n        width: 520px;\r\n        text-align: right;\r\n        padding: 10px;\r\n        margin: 0 auto;\r\n    }\r\n    .ayat-text {\r\n        \r\n    }\r\n    .sura-name {\r\n        text-align: center;\r\n    }\r\n    .line {\r\n    }\r\n.fontQCF_P186 { font-size:36px;font-family:QCF_P186;color:#000;}.ayat8_71 {}\n.ayat8_72 {}\n.ayat8_73 {}\n.line { text-align: center; }.ayat-text {  }.ayat-text:hover { color: #08e8de !important; cursor: pointer; cursor: pointer !important; }.invisible-text { color: white !important;\r\n                            -moz-user-select: none;\r\n                            -webkit-user-select: none;\r\n                            -ms-user-select: none;\r\n                            user-select: none;\r\n                            -o-user-select: none;}.invisible-text:hover { color: white !important;\r\n                            cursor: default !important;\r\n                            -moz-user-select: none;\r\n                            -webkit-user-select: none;\r\n                            -ms-user-select: none;\r\n                            user-select: none;\r\n                            -o-user-select: none;}\r\n</style>\r\n<!-- End inline CSS -->\r\n\r\n<!-- Begin embedded font definitions -->\r\n<style id=\"fonts1\" type=\"text/css\" >\r\n@font-face {font-family: QCF_P186; src: url(\"https://imanakhov.github.io/fonts/qcf_p186.ttf\") format(\"opentype\");}\r\n</style>\r\n<!-- End embedded font definitions -->\r\n\r\n<!-- Begin text definitions (Positioned/styled in CSS) -->\r\n<div class=\"page\"><div class=\"line\"><span class=\"fontQCF_P186 ayat-text invisible-text sura8 ayat8_71\">ﭰ</span><span class=\"fontQCF_P186 ayat-text invisible-text sura8 ayat8_71\">ﭱ</span><span class=\"fontQCF_P186 ayat-text invisible-text sura8 ayat8_71\">ﭲ</span><span class=\"fontQCF_P186 ayat-text invisible-text sura8 ayat8_71\">ﭳ</span><span class=\"fontQCF_P186 ayat-text invisible-text sura8 ayat8_71\">ﭴ</span><span class=\"fontQCF_P186 ayat-text invisible-text sura8 ayat8_71\">ﭵ</span><span class=\"fontQCF_P186 ayat-text invisible-text sura8 ayat8_71\">ﭶ</span><span class=\"fontQCF_P186 ayat-text invisible-text sura8 ayat8_71\">ﭷ</span><span class=\"fontQCF_P186 ayat-text invisible-text sura8 ayat8_71\">ﭸ</span><span class=\"fontQCF_P186 ayat-text invisible-text sura8 ayat8_71\">ﭹ</span><span class=\"fontQCF_P186 ayat-text sura8 ayat8_72\">ﭺ</span><span class=\"fontQCF_P186 ayat-text sura8 ayat8_72\">ﭻ</span></div><div class=\"line\"><span class=\"fontQCF_P186 ayat-text sura8 ayat8_72\">ﭼ</span><span class=\"fontQCF_P186 ayat-text sura8 ayat8_72\">ﭽ</span><span class=\"fontQCF_P186 ayat-text sura8 ayat8_72\">ﭾ</span><span class=\"fontQCF_P186 ayat-text sura8 ayat8_72\">ﭿ</span><span class=\"fontQCF_P186 ayat-text sura8 ayat8_72\">ﮀ</span><span class=\"fontQCF_P186 ayat-text sura8 ayat8_72\">ﮁ</span><span class=\"fontQCF_P186 ayat-text sura8 ayat8_72\">ﮂ</span></div><div class=\"line\"><span class=\"fontQCF_P186 ayat-text sura8 ayat8_72\">ﮃ</span><span class=\"fontQCF_P186 ayat-text sura8 ayat8_72\">ﮄ</span><span class=\"fontQCF_P186 ayat-text sura8 ayat8_72\">ﮅ</span><span class=\"fontQCF_P186 ayat-text sura8 ayat8_72\">ﮆ</span><span class=\"fontQCF_P186 ayat-text sura8 ayat8_72\">ﮇ</span><span class=\"fontQCF_P186 ayat-text sura8 ayat8_72\">ﮈ</span><span class=\"fontQCF_P186 ayat-text sura8 ayat8_72\">ﮉ</span><span class=\"fontQCF_P186 ayat-text sura8 ayat8_72\">ﮊ</span><span class=\"fontQCF_P186 ayat-text sura8 ayat8_72\">ﮋ</span><span class=\"fontQCF_P186 ayat-text sura8 ayat8_72\">ﮌ</span></div><div class=\"line\"><span class=\"fontQCF_P186 ayat-text sura8 ayat8_72\">ﮍ</span><span class=\"fontQCF_P186 ayat-text sura8 ayat8_72\">ﮎ</span><span class=\"fontQCF_P186 ayat-text sura8 ayat8_72\">ﮏ</span><span class=\"fontQCF_P186 ayat-text sura8 ayat8_72\">ﮐ</span><span class=\"fontQCF_P186 ayat-text sura8 ayat8_72\">ﮑ</span><span class=\"fontQCF_P186 ayat-text sura8 ayat8_72\">ﮒ</span><span class=\"fontQCF_P186 ayat-text sura8 ayat8_72\">ﮓ</span><span class=\"fontQCF_P186 ayat-text sura8 ayat8_72\">ﮔ</span><span class=\"fontQCF_P186 ayat-text sura8 ayat8_72\">ﮕ</span><span class=\"fontQCF_P186 ayat-text sura8 ayat8_72\">ﮖ</span><span class=\"fontQCF_P186 ayat-text sura8 ayat8_72\">ﮗ</span><span class=\"fontQCF_P186 ayat-text sura8 ayat8_72\">ﮘ</span></div><div class=\"line\"><span class=\"fontQCF_P186 ayat-text sura8 ayat8_72\">ﮙ</span><span class=\"fontQCF_P186 ayat-text sura8 ayat8_72\">ﮚ</span><span class=\"fontQCF_P186 ayat-text sura8 ayat8_72\">ﮛ</span><span class=\"fontQCF_P186 ayat-text sura8 ayat8_72\">ﮜ</span><span class=\"fontQCF_P186 ayat-text sura8 ayat8_72\">ﮝ</span><span class=\"fontQCF_P186 ayat-text sura8 ayat8_72\">ﮞ</span><span class=\"fontQCF_P186 ayat-text sura8 ayat8_72\">ﮟ</span><span class=\"fontQCF_P186 ayat-text sura8 ayat8_72\">ﮠ</span><span class=\"fontQCF_P186 ayat-text sura8 ayat8_72\">ﮡ</span></div><div class=\"line\"><span class=\"fontQCF_P186 ayat-text sura8 ayat8_72\">ﮢ</span><span class=\"fontQCF_P186 ayat-text sura8 ayat8_72\">ﮣ</span><span class=\"fontQCF_P186 ayat-text sura8 ayat8_72\">ﮤ</span><span class=\"fontQCF_P186 ayat-text sura8 ayat8_72\">ﮥ</span><span class=\"fontQCF_P186 ayat-text sura8 ayat8_72\">ﮦ</span><span class=\"fontQCF_P186 ayat-text sura8 ayat8_72\">ﮧ</span><span class=\"fontQCF_P186 ayat-text sura8 ayat8_72\">ﮨ</span><span class=\"fontQCF_P186 ayat-text sura8 ayat8_72\">ﮩ</span><span class=\"fontQCF_P186 ayat-text sura8 ayat8_72\">ﮪ</span><span class=\"fontQCF_P186 ayat-text invisible-text sura8 ayat8_73\">ﮫ</span></div></div>\r\n<!-- End text definitions -->\r\n</div>\r\n</body>\r\n</html>\r\n"},{"page":186,"sura":8,"ayat":73,"html":"<!DOCTYPE html >\r\n<html lang=\"en\">\r\n<head>\r\n<meta http-equiv=\"X-UA-Compatible\" content=\"IE=Edge\" />\r\n<meta charset=\"utf-8\" />\r\n</head>\r\n\r\n<body style=\"\">\r\n<div class=\"quran-container\">\r\n<!-- Begin shared CSS values -->\r\n<style id=\"classes\" type=\"text/css\" >\r\n    .quran-container {\r\n        width: 520px;\r\n        text-align: right;\r\n        padding: 10px;\r\n        margin: 0 auto;\r\n    }\r\n    .ayat-text {\r\n        \r\n    }\r\n    .sura-name {\r\n        text-align: center;\r\n    }\r\n    .line {\r\n    }\r\n.fontQCF_P186 { font-size:36px;font-family:QCF_P186;color:#000;}.ayat8_72 {}\n.ayat8_73 {}\n.ayat8_74 {}\n.line { text-align: center; }.ayat-text {  }.ayat-text:hover { color: #08e8de !important; cursor: pointer; cursor: pointer !important; }.invisible-text { color: white !important;\r\n                            -moz-user-select: none;\r\n                            -webkit-user-select: none;\r\n                            -ms-user-select: none;\r\n                            user-select: none;\r\n                            -o-user-select: none;}.invisible-text:hover { color: white !important;\r\n                            cursor: default !important;\r\n                            -moz-user-select: none;\r\n                            -webkit-user-select: none;\r\n                            -ms-user-select: none;\r\n                            user-select: none;\r\n                            -o-user-select: none;}\r\n</style>\r\n<!-- End inline CSS -->\r\n\r\n<!-- Begin embedded font definitions -->\r\n<style id=\"fonts1\" type=\"text/css\" >\r\n@font-face {font-family: QCF_P186; src: url(\"https://imanakhov.github.io/fonts/qcf_p186.ttf\") format(\"opentype\");}\r\n</style>\r\n<!-- End embedded font definitions -->\r\n\r\n<!-- Begin text definitions (Positioned/styled in CSS) -->\r\n<div class=\"page\"><div class=\"line\"><span class=\"fontQCF_P186 ayat-text invisible-text sura8 ayat8_72\">ﮢ</span><span class=\"fontQCF_P186 ayat-text invisible-text sura8 ayat8_72\">ﮣ</span><span class=\"fontQCF_P186 ayat-text invisible-text sura8 ayat8_72\">ﮤ</span><span class=\"fontQCF_P186 ayat-text invisible-text sura8 ayat8_72\">ﮥ</span><span class=\"fontQCF_P186 ayat-text invisible-text sura8 ayat8_72\">ﮦ</span><span class=\"fontQCF_P186 ayat-text invisible-text sura8 ayat8_72\">ﮧ</span><span class=\"fontQCF_P186 ayat-text invisible-text sura8 ayat8_72\">ﮨ</span><span class=\"fontQCF_P186 ayat-text invisible-text sura8 ayat8_72\">ﮩ</span><span class=\"fontQCF_P186 ayat-text invisible-text sura8 ayat8_72\">ﮪ</span><span class=\"fontQCF_P186 ayat-text sura8 ayat8_73\">ﮫ</span></div><div class=\"line\"><span class=\"fontQCF_P186 ayat-text sura8 ayat8_73\">ﮬ</span><span class=\"fontQCF_P186 ayat-text sura8 ayat8_73\">ﮭ</span><span class=\"fontQCF_P186 ayat-text sura8 ayat8_73\">ﮮ</span><span class=\"fontQCF_P186 ayat-text sura8 ayat8_73\">ﮯ</span><span class=\"fontQCF_P186 ayat-text sura8 ayat8_73\">ﮰ</span><span class=\"fontQCF_P186 ayat-text sura8 ayat8_73\">ﮱ</span><span class=\"fontQCF_P186 ayat-text sura8 ayat8_73\">ﯓ</span><span class=\"fontQCF_P186 ayat-text sura8 ayat8_73\">ﯔ</span><span class=\"fontQCF_P186 ayat-text sura8 ayat8_73\">ﯕ</span><span class=\"fontQCF_P186 ayat-text sura8 ayat8_73\">ﯖ</span></div><div class=\"line\"><span class=\"fontQCF_P186 ayat-text sura8 ayat8_73\">ﯗ</span><span class=\"fontQCF_P186 ayat-text sura8 ayat8_73\">ﯘ</span><span class=\"fontQCF_P186 ayat-text sura8 ayat8_73\">ﯙ</span><span class=\"fontQCF_P186 ayat-text sura8 ayat8_73\">ﯚ</span><span class=\"fontQCF_P186 ayat-text invisible-text sura8 ayat8_74\">ﯛ</span><span class=\"fontQCF_P186 ayat-text invisible-text sura8 ayat8_74\">ﯜ</span><span class=\"fontQCF_P186 ayat-text invisible-text sura8 ayat8_74\">ﯝ</span></div></div>\r\n<!-- End text definitions -->\r\n</div>\r\n</body>\r\n</html>\r\n"},{"page":186,"sura":8,"ayat":74,"html":"<!DOCTYPE html >\r\n<html lang=\"en\">\r\n<head>\r\n<meta http-equiv=\"X-UA-Compatible\" content=\"IE=Edge\" />\r\n<meta charset=\"utf-8\" />\r\n</head>\r\n\r\n<body style=\"\">\r\n<div class=\"quran-container\">\r\n<!-- Begin shared CSS values -->\r\n<style id=\"classes\" type=\"text/css\" >\r\n    .quran-container {\r\n        width: 520px;\r\n        text-align: right;\r\n        padding: 10px;\r\n        margin: 0 auto;\r\n    }\r\n    .ayat-text {\r\n        \r\n    }\r\n    .sura-name {\r\n        text-align: center;\r\n    }\r\n    .line {\r\n    }\r\n.fontQCF_P186 { font-size:36px;font-family:QCF_P186;color:#000;}.ayat8_73 {}\n.ayat8_74 {}\n.ayat8_75 {}\n.line { text-align: center; }.ayat-text {  }.ayat-text:hover { color: #08e8de !important; cursor: pointer; cursor: pointer !important; }.invisible-text { color: white !important;\r\n                            -moz-user-select: none;\r\n                            -webkit-user-select: none;\r\n                            -ms-user-select: none;\r\n                            user-select: none;\r\n                            -o-user-select: none;}.invisible-text:hover { color: white !important;\r\n                            cursor: default !important;\r\n                            -moz-user-select: none;\r\n                            -webkit-user-select: none;\r\n                            -ms-user-select: none;\r\n                            user-select: none;\r\n                            -o-user-select: none;}\r\n</style>\r\n<!-- End inline CSS -->\r\n\r\n<!-- Begin embedded font definitions -->\r\n<style id=\"fonts1\" type=\"text/css\" >\r\n@font-face {font-family: QCF_P186; src: url(\"https://imanakhov.github.io/fonts/qcf_p186.ttf\") format(\"opentype\");}\r\n</style>\r\n<!-- End embedded font definitions -->\r\n\r\n<!-- Begin text definitions (Positioned/styled in CSS) -->\r\n<div class=\"page\"><div class=\"line\"><span class=\"fontQCF_P186 ayat-text invisible-text sura8 ayat8_73\">ﯗ</span><span class=\"fontQCF_P186 ayat-text invisible-text sura8 ayat8_73\">ﯘ</span><span class=\"fontQCF_P186 ayat-text invisible-text sura8 ayat8_73\">ﯙ</span><span class=\"fontQCF_P186 ayat-text invisible-text sura8 ayat8_73\">ﯚ</span><span class=\"fontQCF_P186 ayat-text sura8 ayat8_74\">ﯛ</span><span class=\"fontQCF_P186 ayat-text sura8 ayat8_74\">ﯜ</span><span class=\"fontQCF_P186 ayat-text sura8 ayat8_74\">ﯝ</span></div><div class=\"line\"><span class=\"fontQCF_P186 ayat-text sura8 ayat8_74\">ﯞ</span><span class=\"fontQCF_P186 ayat-text sura8 ayat8_74\">ﯟ</span><span class=\"fontQCF_P186 ayat-text sura8 ayat8_74\">ﯠ</span><span class=\"fontQCF_P186 ayat-text sura8 ayat8_74\">ﯡ</span><span class=\"fontQCF_P186 ayat-text sura8 ayat8_74\">ﯢ</span><span class=\"fontQCF_P186 ayat-text sura8 ayat8_74\">ﯣ</span><span class=\"fontQCF_P186 ayat-text sura8 ayat8_74\">ﯤ</span><span class=\"fontQCF_P186 ayat-text sura8 ayat8_74\">ﯥ</span><span class=\"fontQCF_P186 ayat-text sura8 ayat8_74\">ﯦ</span></div><div class=\"line\"><span class=\"fontQCF_P186 ayat-text sura8 ayat8_74\">ﯧ</span><span class=\"fontQCF_P186 ayat-text sura8 ayat8_74\">ﯨ</span><span class=\"fontQCF_P186 ayat-text sura8 ayat8_74\">ﯩ</span><span class=\"fontQCF_P186 ayat-text sura8 ayat8_74\">ﯪ</span><span class=\"fontQCF_P186 ayat-text sura8 ayat8_74\">ﯫ</span><span class=\"fontQCF_P186 ayat-text sura8 ayat8_74\">ﯬ</span><span class=\"fontQCF_P186 ayat-text sura8 ayat8_74\">ﯭ</span><span class=\"fontQCF_P186 ayat-text sura8 ayat8_74\">ﯮ</span><span class=\"fontQCF_P186 ayat-text invisible-text sura8 ayat8_75\">ﯯ</span><span class=\"fontQCF_P186 ayat-text invisible-text sura8 ayat8_75\">ﯰ</span><span class=\"fontQCF_P186 ayat-text invisible-text sura8 ayat8_75\">ﯱ</span></div></div>\r\n<!-- End text definitions -->\r\n</div>\r\n</body>\r\n</html>\r\n"},{"page":186,"sura":8,"ayat":75,"html":"<!DOCTYPE html >\r\n<html lang=\"en\">\r\n<head>\r\n<meta http-equiv=\"X-UA-Compatible\" content=\"IE=Edge\" />\r\n<meta charset=\"utf-8\" />\r\n</head>\r\n\r\n<body style=\"\">\r\n<div class=\"quran-container\">\r\n<!-- Begin shared CSS values -->\r\n<style id=\"classes\" type=\"text/css\" >\r\n    .quran-container {\r\n        width: 520px;\r\n        text-align: right;\r\n        padding: 10px;\r\n        margin: 0 auto;\r\n    }\r\n    .ayat-text {\r\n        \r\n    }\r\n    .sura-name {\r\n        text-align: center;\r\n    }\r\n    .line {\r\n    }\r\n.fontQCF_P186 { font-size:36px;font-family:QCF_P186;color:#000;}.ayat8_74 {}\n.ayat8_75 {}\n.line { text-align: center; }.ayat-text {  }.ayat-text:hover { color: #08e8de !important; cursor: pointer; cursor: pointer !important; }.invisible-text { color: white !important;\r\n                            -moz-user-select: none;\r\n                            -webkit-user-select: none;\r\n                            -ms-user-select: none;\r\n                            user-select: none;\r\n                            -o-user-select: none;}.invisible-text:hover { color: white !important;\r\n                            cursor: default !important;\r\n                            -moz-user-select: none;\r\n                            -webkit-user-select: none;\r\n                            -ms-user-select: none;\r\n                            user-select: none;\r\n                            -o-user-select: none;}\r\n</style>\r\n<!-- End inline CSS -->\r\n\r\n<!-- Begin embedded font definitions -->\r\n<style id=\"fonts1\" type=\"text/css\" >\r\n@font-face {font-family: QCF_P186; src: url(\"https://imanakhov.github.io/fonts/qcf_p186.ttf\") format(\"opentype\");}\r\n</style>\r\n<!-- End embedded font definitions -->\r\n\r\n<!-- Begin text definitions (Positioned/styled in CSS) -->\r\n<div class=\"page\"><div class=\"line\"><span class=\"fontQCF_P186 ayat-text invisible-text sura8 ayat8_74\">ﯧ</span><span class=\"fontQCF_P186 ayat-text invisible-text sura8 ayat8_74\">ﯨ</span><span class=\"fontQCF_P186 ayat-text invisible-text sura8 ayat8_74\">ﯩ</span><span class=\"fontQCF_P186 ayat-text invisible-text sura8 ayat8_74\">ﯪ</span><span class=\"fontQCF_P186 ayat-text invisible-text sura8 ayat8_74\">ﯫ</span><span class=\"fontQCF_P186 ayat-text invisible-text sura8 ayat8_74\">ﯬ</span><span class=\"fontQCF_P186 ayat-text invisible-text sura8 ayat8_74\">ﯭ</span><span class=\"fontQCF_P186 ayat-text invisible-text sura8 ayat8_74\">ﯮ</span><span class=\"fontQCF_P186 ayat-text sura8 ayat8_75\">ﯯ</span><span class=\"fontQCF_P186 ayat-text sura8 ayat8_75\">ﯰ</span><span class=\"fontQCF_P186 ayat-text sura8 ayat8_75\">ﯱ</span></div><div class=\"line\"><span class=\"fontQCF_P186 ayat-text sura8 ayat8_75\">ﯲ</span><span class=\"fontQCF_P186 ayat-text sura8 ayat8_75\">ﯳ</span><span class=\"fontQCF_P186 ayat-text sura8 ayat8_75\">ﯴ</span><span class=\"fontQCF_P186 ayat-text sura8 ayat8_75\">ﯵ</span><span class=\"fontQCF_P186 ayat-text sura8 ayat8_75\">ﯶ</span><span class=\"fontQCF_P186 ayat-text sura8 ayat8_75\">ﯷ</span><span class=\"fontQCF_P186 ayat-text sura8 ayat8_75\">ﯸ</span><span class=\"fontQCF_P186 ayat-text sura8 ayat8_75\">ﯹ</span><span class=\"fontQCF_P186 ayat-text sura8 ayat8_75\">ﯺ</span></div><div class=\"line\"><span class=\"fontQCF_P186 ayat-text sura8 ayat8_75\">ﯻ</span><span class=\"fontQCF_P186 ayat-text sura8 ayat8_75\">ﯼ</span><span class=\"fontQCF_P186 ayat-text sura8 ayat8_75\">ﯽ</span><span class=\"fontQCF_P186 ayat-text sura8 ayat8_75\">ﯾ</span><span class=\"fontQCF_P186 ayat-text sura8 ayat8_75\">ﯿ</span><span class=\"fontQCF_P186 ayat-text sura8 ayat8_75\">ﰀ</span><span class=\"fontQCF_P186 ayat-text sura8 ayat8_75\">ﰁ</span><span class=\"fontQCF_P186 ayat-text sura8 ayat8_75\">ﰂ</span><span class=\"fontQCF_P186 ayat-text sura8 ayat8_75\">ﰃ</span><span class=\"fontQCF_P186 ayat-text sura8 ayat8_75\">ﰄ</span><span class=\"fontQCF_P186 ayat-text sura8 ayat8_75\">ﰅ</span><span class=\"fontQCF_P186 ayat-text sura8 ayat8_75\">ﰆ</span><span class=\"fontQCF_P186 ayat-text sura8 ayat8_75\">ﰇ</span></div></div>\r\n<!-- End text definitions -->\r\n</div>\r\n</body>\r\n</html>\r\n"}]