[{"page":235,"sura":11,"ayat":118,"html":"<!DOCTYPE html >\r\n<html lang=\"en\">\r\n<head>\r\n<meta http-equiv=\"X-UA-Compatible\" content=\"IE=Edge\" />\r\n<meta charset=\"utf-8\" />\r\n</head>\r\n\r\n<body style=\"\">\r\n<div class=\"quran-container\">\r\n<!-- Begin shared CSS values -->\r\n<style id=\"classes\" type=\"text/css\" >\r\n    .quran-container {\r\n        width: 520px;\r\n        text-align: right;\r\n        padding: 10px;\r\n        margin: 0 auto;\r\n    }\r\n    .ayat-text {\r\n        \r\n    }\r\n    .sura-name {\r\n        text-align: center;\r\n    }\r\n    .line {\r\n    }\r\n.fontQCF_P235 { font-size:36px;font-family:QCF_P235;color:#000;}.ayat11_118 {}\n.ayat11_119 {}\n.line { text-align: center; }.ayat-text {  }.ayat-text:hover { color: #08e8de !important; cursor: pointer; cursor: pointer !important; }.invisible-text { color: white !important;\r\n                            -moz-user-select: none;\r\n                            -webkit-user-select: none;\r\n                            -ms-user-select: none;\r\n                            user-select: none;\r\n                            -o-user-select: none;}.invisible-text:hover { color: white !important;\r\n                            cursor: default !important;\r\n                            -moz-user-select: none;\r\n                            -webkit-user-select: none;\r\n                            -ms-user-select: none;\r\n                            user-select: none;\r\n                            -o-user-select: none;}\r\n</style>\r\n<!-- End inline CSS -->\r\n\r\n<!-- Begin embedded font definitions -->\r\n<style id=\"fonts1\" type=\"text/css\" >\r\n@font-face {font-family: QCF_P235; src: url(\"https://imanakhov.github.io/fonts/qcf_p235.ttf\") format(\"opentype\");}\r\n</style>\r\n<!-- End embedded font definitions -->\r\n\r\n<!-- Begin text definitions (Positioned/styled in CSS) -->\r\n<div class=\"page\"><div class=\"line\"><span class=\"fontQCF_P235 ayat-text sura11 ayat11_118\">ﭑ</span><span class=\"fontQCF_P235 ayat-text sura11 ayat11_118\">ﭒ</span><span class=\"fontQCF_P235 ayat-text sura11 ayat11_118\">ﭓ</span><span class=\"fontQCF_P235 ayat-text sura11 ayat11_118\">ﭔ</span><span class=\"fontQCF_P235 ayat-text sura11 ayat11_118\">ﭕ</span><span class=\"fontQCF_P235 ayat-text sura11 ayat11_118\">ﭖ</span><span class=\"fontQCF_P235 ayat-text sura11 ayat11_118\">ﭗ</span><span class=\"fontQCF_P235 ayat-text sura11 ayat11_118\">ﭘ</span><span class=\"fontQCF_P235 ayat-text sura11 ayat11_118\">ﭙ</span><span class=\"fontQCF_P235 ayat-text sura11 ayat11_118\">ﭚ</span><span class=\"fontQCF_P235 ayat-text sura11 ayat11_118\">ﭛ</span></div><div class=\"line\"><span class=\"fontQCF_P235 ayat-text sura11 ayat11_118\">ﭜ</span><span class=\"fontQCF_P235 ayat-text invisible-text sura11 ayat11_119\">ﭝ</span><span class=\"fontQCF_P235 ayat-text invisible-text sura11 ayat11_119\">ﭞ</span><span class=\"fontQCF_P235 ayat-text invisible-text sura11 ayat11_119\">ﭟ</span><span class=\"fontQCF_P235 ayat-text invisible-text sura11 ayat11_119\">ﭠ</span><span class=\"fontQCF_P235 ayat-text invisible-text sura11 ayat11_119\">ﭡ</span><span class=\"fontQCF_P235 ayat-text invisible-text sura11 ayat11_119\">ﭢ</span><span class=\"fontQCF_P235 ayat-text invisible-text sura11 ayat11_119\">ﭣ</span><span class=\"fontQCF_P235 ayat-text invisible-text sura11 ayat11_119\">ﭤ</span><span class=\"fontQCF_P235 ayat-text invisible-text sura11 ayat11_119\">ﭥ</span><span class=\"fontQCF_P235 ayat-text invisible-text sura11 ayat11_119\">ﭦ</span><span class=\"fontQCF_P235 ayat-text invisible-text sura11 ayat11_119\">ﭧ</span></div></div>\r\n<!-- End text definitions -->\r\n</div>\r\n</body>\r\n</html>\r\n"},{"page":235,"sura":11,"ayat":119,"html":"<!DOCTYPE html >\r\n<html lang=\"en\">\r\n<head>\r\n<meta http-equiv=\"X-UA-Compatible\" content=\"IE=Edge\" />\r\n<meta charset=\"utf-8\" />\r\n</head>\r\n\r\n<body style=\"\">\r\n<div class=\"quran-container\">\r\n<!-- Begin shared CSS values -->\r\n<style id=\"classes\" type=\"text/css\" >\r\n    .quran-container {\r\n        width: 520px;\r\n        text-align: right;\r\n        padding: 10px;\r\n        margin: 0 auto;\r\n    }\r\n    .ayat-text {\r\n        \r\n    }\r\n    .sura-name {\r\n        text-align: center;\r\n    }\r\n    .line {\r\n    }\r\n.fontQCF_P235 { font-size:36px;font-family:QCF_P235;color:#000;}.ayat11_118 {}\n.ayat11_119 {}\n.ayat11_120 {}\n.line { text-align: center; }.ayat-text {  }.ayat-text:hover { color: #08e8de !important; cursor: pointer; cursor: pointer !important; }.invisible-text { color: white !important;\r\n                            -moz-user-select: none;\r\n                            -webkit-user-select: none;\r\n                            -ms-user-select: none;\r\n                            user-select: none;\r\n                            -o-user-select: none;}.invisible-text:hover { color: white !important;\r\n                            cursor: default !important;\r\n                            -moz-user-select: none;\r\n                            -webkit-user-select: none;\r\n                            -ms-user-select: none;\r\n                            user-select: none;\r\n                            -o-user-select: none;}\r\n</style>\r\n<!-- End inline CSS -->\r\n\r\n<!-- Begin embedded font definitions -->\r\n<style id=\"fonts1\" type=\"text/css\" >\r\n@font-face {font-family: QCF_P235; src: url(\"https://imanakhov.github.io/fonts/qcf_p235.ttf\") format(\"opentype\");}\r\n</style>\r\n<!-- End embedded font definitions -->\r\n\r\n<!-- Begin text definitions (Positioned/styled in CSS) -->\r\n<div class=\"page\"><div class=\"line\"><span class=\"fontQCF_P235 ayat-text invisible-text sura11 ayat11_118\">ﭜ</span><span class=\"fontQCF_P235 ayat-text sura11 ayat11_119\">ﭝ</span><span class=\"fontQCF_P235 ayat-text sura11 ayat11_119\">ﭞ</span><span class=\"fontQCF_P235 ayat-text sura11 ayat11_119\">ﭟ</span><span class=\"fontQCF_P235 ayat-text sura11 ayat11_119\">ﭠ</span><span class=\"fontQCF_P235 ayat-text sura11 ayat11_119\">ﭡ</span><span class=\"fontQCF_P235 ayat-text sura11 ayat11_119\">ﭢ</span><span class=\"fontQCF_P235 ayat-text sura11 ayat11_119\">ﭣ</span><span class=\"fontQCF_P235 ayat-text sura11 ayat11_119\">ﭤ</span><span class=\"fontQCF_P235 ayat-text sura11 ayat11_119\">ﭥ</span><span class=\"fontQCF_P235 ayat-text sura11 ayat11_119\">ﭦ</span><span class=\"fontQCF_P235 ayat-text sura11 ayat11_119\">ﭧ</span></div><div class=\"line\"><span class=\"fontQCF_P235 ayat-text sura11 ayat11_119\">ﭨ</span><span class=\"fontQCF_P235 ayat-text sura11 ayat11_119\">ﭩ</span><span class=\"fontQCF_P235 ayat-text sura11 ayat11_119\">ﭪ</span><span class=\"fontQCF_P235 ayat-text sura11 ayat11_119\">ﭫ</span><span class=\"fontQCF_P235 ayat-text sura11 ayat11_119\">ﭬ</span><span class=\"fontQCF_P235 ayat-text sura11 ayat11_119\">ﭭ</span><span class=\"fontQCF_P235 ayat-text sura11 ayat11_119\">ﭮ</span><span class=\"fontQCF_P235 ayat-text invisible-text sura11 ayat11_120\">ﭯ</span><span class=\"fontQCF_P235 ayat-text invisible-text sura11 ayat11_120\">ﭰ</span></div></div>\r\n<!-- End text definitions -->\r\n</div>\r\n</body>\r\n</html>\r\n"},{"page":235,"sura":11,"ayat":120,"html":"<!DOCTYPE html >\r\n<html lang=\"en\">\r\n<head>\r\n<meta http-equiv=\"X-UA-Compatible\" content=\"IE=Edge\" />\r\n<meta charset=\"utf-8\" />\r\n</head>\r\n\r\n<body style=\"\">\r\n<div class=\"quran-container\">\r\n<!-- Begin shared CSS values -->\r\n<style id=\"classes\" type=\"text/css\" >\r\n    .quran-container {\r\n        width: 520px;\r\n        text-align: right;\r\n        padding: 10px;\r\n        margin: 0 auto;\r\n    }\r\n    .ayat-text {\r\n        \r\n    }\r\n    .sura-name {\r\n        text-align: center;\r\n    }\r\n    .line {\r\n    }\r\n.fontQCF_P235 { font-size:36px;font-family:QCF_P235;color:#000;}.ayat11_119 {}\n.ayat11_120 {}\n.ayat11_121 {}\n.line { text-align: center; }.ayat-text {  }.ayat-text:hover { color: #08e8de !important; cursor: pointer; cursor: pointer !important; }.invisible-text { color: white !important;\r\n                            -moz-user-select: none;\r\n                            -webkit-user-select: none;\r\n                            -ms-user-select: none;\r\n                            user-select: none;\r\n                            -o-user-select: none;}.invisible-text:hover { color: white !important;\r\n                            cursor: default !important;\r\n                            -moz-user-select: none;\r\n                            -webkit-user-select: none;\r\n                            -ms-user-select: none;\r\n                            user-select: none;\r\n                            -o-user-select: none;}\r\n</style>\r\n<!-- End inline CSS -->\r\n\r\n<!-- Begin embedded font definitions -->\r\n<style id=\"fonts1\" type=\"text/css\" >\r\n@font-face {font-family: QCF_P235; src: url(\"https://imanakhov.github.io/fonts/qcf_p235.ttf\") format(\"opentype\");}\r\n</style>\r\n<!-- End embedded font definitions -->\r\n\r\n<!-- Begin text definitions (Positioned/styled in CSS) -->\r\n<div class=\"page\"><div class=\"line\"><span class=\"fontQCF_P235 ayat-text invisible-text sura11 ayat11_119\">ﭨ</span><span class=\"fontQCF_P235 ayat-text invisible-text sura11 ayat11_119\">ﭩ</span><span class=\"fontQCF_P235 ayat-text invisible-text sura11 ayat11_119\">ﭪ</span><span class=\"fontQCF_P235 ayat-text invisible-text sura11 ayat11_119\">ﭫ</span><span class=\"fontQCF_P235 ayat-text invisible-text sura11 ayat11_119\">ﭬ</span><span class=\"fontQCF_P235 ayat-text invisible-text sura11 ayat11_119\">ﭭ</span><span class=\"fontQCF_P235 ayat-text invisible-text sura11 ayat11_119\">ﭮ</span><span class=\"fontQCF_P235 ayat-text sura11 ayat11_120\">ﭯ</span><span class=\"fontQCF_P235 ayat-text sura11 ayat11_120\">ﭰ</span></div><div class=\"line\"><span class=\"fontQCF_P235 ayat-text sura11 ayat11_120\">ﭱ</span><span class=\"fontQCF_P235 ayat-text sura11 ayat11_120\">ﭲ</span><span class=\"fontQCF_P235 ayat-text sura11 ayat11_120\">ﭳ</span><span class=\"fontQCF_P235 ayat-text sura11 ayat11_120\">ﭴ</span><span class=\"fontQCF_P235 ayat-text sura11 ayat11_120\">ﭵ</span><span class=\"fontQCF_P235 ayat-text sura11 ayat11_120\">ﭶ</span><span class=\"fontQCF_P235 ayat-text sura11 ayat11_120\">ﭷ</span><span class=\"fontQCF_P235 ayat-text sura11 ayat11_120\">ﭸ</span><span class=\"fontQCF_P235 ayat-text sura11 ayat11_120\">ﭹ</span><span class=\"fontQCF_P235 ayat-text sura11 ayat11_120\">ﭺ</span><span class=\"fontQCF_P235 ayat-text sura11 ayat11_120\">ﭻ</span><span class=\"fontQCF_P235 ayat-text sura11 ayat11_120\">ﭼ</span></div><div class=\"line\"><span class=\"fontQCF_P235 ayat-text sura11 ayat11_120\">ﭽ</span><span class=\"fontQCF_P235 ayat-text sura11 ayat11_120\">ﭾ</span><span class=\"fontQCF_P235 ayat-text sura11 ayat11_120\">ﭿ</span><span class=\"fontQCF_P235 ayat-text sura11 ayat11_120\">ﮀ</span><span class=\"fontQCF_P235 ayat-text sura11 ayat11_120\">ﮁ</span><span class=\"fontQCF_P235 ayat-text invisible-text sura11 ayat11_121\">ﮂ</span><span class=\"fontQCF_P235 ayat-text invisible-text sura11 ayat11_121\">ﮃ</span><span class=\"fontQCF_P235 ayat-text invisible-text sura11 ayat11_121\">ﮄ</span><span class=\"fontQCF_P235 ayat-text invisible-text sura11 ayat11_121\">ﮅ</span></div></div>\r\n<!-- End text definitions -->\r\n</div>\r\n</body>\r\n</html>\r\n"},{"page":235,"sura":11,"ayat":121,"html":"<!DOCTYPE html >\r\n<html lang=\"en\">\r\n<head>\r\n<meta http-equiv=\"X-UA-Compatible\" content=\"IE=Edge\" />\r\n<meta charset=\"utf-8\" />\r\n</head>\r\n\r\n<body style=\"\">\r\n<div class=\"quran-container\">\r\n<!-- Begin shared CSS values -->\r\n<style id=\"classes\" type=\"text/css\" >\r\n    .quran-container {\r\n        width: 520px;\r\n        text-align: right;\r\n        padding: 10px;\r\n        margin: 0 auto;\r\n    }\r\n    .ayat-text {\r\n        \r\n    }\r\n    .sura-name {\r\n        text-align: center;\r\n    }\r\n    .line {\r\n    }\r\n.fontQCF_P235 { font-size:36px;font-family:QCF_P235;color:#000;}.ayat11_120 {}\n.ayat11_121 {}\n.ayat11_122 {}\n.line { text-align: center; }.ayat-text {  }.ayat-text:hover { color: #08e8de !important; cursor: pointer; cursor: pointer !important; }.invisible-text { color: white !important;\r\n                            -moz-user-select: none;\r\n                            -webkit-user-select: none;\r\n                            -ms-user-select: none;\r\n                            user-select: none;\r\n                            -o-user-select: none;}.invisible-text:hover { color: white !important;\r\n                            cursor: default !important;\r\n                            -moz-user-select: none;\r\n                            -webkit-user-select: none;\r\n                            -ms-user-select: none;\r\n                            user-select: none;\r\n                            -o-user-select: none;}\r\n</style>\r\n<!-- End inline CSS -->\r\n\r\n<!-- Begin embedded font definitions -->\r\n<style id=\"fonts1\" type=\"text/css\" >\r\n@font-face {font-family: QCF_P235; src: url(\"https://imanakhov.github.io/fonts/qcf_p235.ttf\") format(\"opentype\");}\r\n</style>\r\n<!-- End embedded font definitions -->\r\n\r\n<!-- Begin text definitions (Positioned/styled in CSS) -->\r\n<div class=\"page\"><div class=\"line\"><span class=\"fontQCF_P235 ayat-text invisible-text sura11 ayat11_120\">ﭽ</span><span class=\"fontQCF_P235 ayat-text invisible-text sura11 ayat11_120\">ﭾ</span><span class=\"fontQCF_P235 ayat-text invisible-text sura11 ayat11_120\">ﭿ</span><span class=\"fontQCF_P235 ayat-text invisible-text sura11 ayat11_120\">ﮀ</span><span class=\"fontQCF_P235 ayat-text invisible-text sura11 ayat11_120\">ﮁ</span><span class=\"fontQCF_P235 ayat-text sura11 ayat11_121\">ﮂ</span><span class=\"fontQCF_P235 ayat-text sura11 ayat11_121\">ﮃ</span><span class=\"fontQCF_P235 ayat-text sura11 ayat11_121\">ﮄ</span><span class=\"fontQCF_P235 ayat-text sura11 ayat11_121\">ﮅ</span></div><div class=\"line\"><span class=\"fontQCF_P235 ayat-text sura11 ayat11_121\">ﮆ</span><span class=\"fontQCF_P235 ayat-text sura11 ayat11_121\">ﮇ</span><span class=\"fontQCF_P235 ayat-text sura11 ayat11_121\">ﮈ</span><span class=\"fontQCF_P235 ayat-text sura11 ayat11_121\">ﮉ</span><span class=\"fontQCF_P235 ayat-text sura11 ayat11_121\">ﮊ</span><span class=\"fontQCF_P235 ayat-text sura11 ayat11_121\">ﮋ</span><span class=\"fontQCF_P235 ayat-text invisible-text sura11 ayat11_122\">ﮌ</span><span class=\"fontQCF_P235 ayat-text invisible-text sura11 ayat11_122\">ﮍ</span><span class=\"fontQCF_P235 ayat-text invisible-text sura11 ayat11_122\">ﮎ</span></div></div>\r\n<!-- End text definitions -->\r\n</div>\r\n</body>\r\n</html>\r\n"},{"page":235,"sura":11,"ayat":122,"html":"<!DOCTYPE html >\r\n<html lang=\"en\">\r\n<head>\r\n<meta http-equiv=\"X-UA-Compatible\" content=\"IE=Edge\" />\r\n<meta charset=\"utf-8\" />\r\n</head>\r\n\r\n<body style=\"\">\r\n<div class=\"quran-container\">\r\n<!-- Begin shared CSS values -->\r\n<style id=\"classes\" type=\"text/css\" >\r\n    .quran-container {\r\n        width: 520px;\r\n        text-align: right;\r\n        padding: 10px;\r\n        margin: 0 auto;\r\n    }\r\n    .ayat-text {\r\n        \r\n    }\r\n    .sura-name {\r\n        text-align: center;\r\n    }\r\n    .line {\r\n    }\r\n.fontQCF_P235 { font-size:36px;font-family:QCF_P235;color:#000;}.ayat11_121 {}\n.ayat11_122 {}\n.ayat11_123 {}\n.line { text-align: center; }.ayat-text {  }.ayat-text:hover { color: #08e8de !important; cursor: pointer; cursor: pointer !important; }.invisible-text { color: white !important;\r\n                            -moz-user-select: none;\r\n                            -webkit-user-select: none;\r\n                            -ms-user-select: none;\r\n                            user-select: none;\r\n                            -o-user-select: none;}.invisible-text:hover { color: white !important;\r\n                            cursor: default !important;\r\n                            -moz-user-select: none;\r\n                            -webkit-user-select: none;\r\n                            -ms-user-select: none;\r\n                            user-select: none;\r\n                            -o-user-select: none;}\r\n</style>\r\n<!-- End inline CSS -->\r\n\r\n<!-- Begin embedded font definitions -->\r\n<style id=\"fonts1\" type=\"text/css\" >\r\n@font-face {font-family: QCF_P235; src: url(\"https://imanakhov.github.io/fonts/qcf_p235.ttf\") format(\"opentype\");}\r\n</style>\r\n<!-- End embedded font definitions -->\r\n\r\n<!-- Begin text definitions (Positioned/styled in CSS) -->\r\n<div class=\"page\"><div class=\"line\"><span class=\"fontQCF_P235 ayat-text invisible-text sura11 ayat11_121\">ﮆ</span><span class=\"fontQCF_P235 ayat-text invisible-text sura11 ayat11_121\">ﮇ</span><span class=\"fontQCF_P235 ayat-text invisible-text sura11 ayat11_121\">ﮈ</span><span class=\"fontQCF_P235 ayat-text invisible-text sura11 ayat11_121\">ﮉ</span><span class=\"fontQCF_P235 ayat-text invisible-text sura11 ayat11_121\">ﮊ</span><span class=\"fontQCF_P235 ayat-text invisible-text sura11 ayat11_121\">ﮋ</span><span class=\"fontQCF_P235 ayat-text sura11 ayat11_122\">ﮌ</span><span class=\"fontQCF_P235 ayat-text sura11 ayat11_122\">ﮍ</span><span class=\"fontQCF_P235 ayat-text sura11 ayat11_122\">ﮎ</span></div><div class=\"line\"><span class=\"fontQCF_P235 ayat-text sura11 ayat11_122\">ﮏ</span><span class=\"fontQCF_P235 ayat-text invisible-text sura11 ayat11_123\">ﮐ</span><span class=\"fontQCF_P235 ayat-text invisible-text sura11 ayat11_123\">ﮑ</span><span class=\"fontQCF_P235 ayat-text invisible-text sura11 ayat11_123\">ﮒ</span><span class=\"fontQCF_P235 ayat-text invisible-text sura11 ayat11_123\">ﮓ</span><span class=\"fontQCF_P235 ayat-text invisible-text sura11 ayat11_123\">ﮔ</span><span class=\"fontQCF_P235 ayat-text invisible-text sura11 ayat11_123\">ﮕ</span><span class=\"fontQCF_P235 ayat-text invisible-text sura11 ayat11_123\">ﮖ</span><span class=\"fontQCF_P235 ayat-text invisible-text sura11 ayat11_123\">ﮗ</span></div></div>\r\n<!-- End text definitions -->\r\n</div>\r\n</body>\r\n</html>\r\n"},{"page":235,"sura":11,"ayat":123,"html":"<!DOCTYPE html >\r\n<html lang=\"en\">\r\n<head>\r\n<meta http-equiv=\"X-UA-Compatible\" content=\"IE=Edge\" />\r\n<meta charset=\"utf-8\" />\r\n</head>\r\n\r\n<body style=\"\">\r\n<div class=\"quran-container\">\r\n<!-- Begin shared CSS values -->\r\n<style id=\"classes\" type=\"text/css\" >\r\n    .quran-container {\r\n        width: 520px;\r\n        text-align: right;\r\n        padding: 10px;\r\n        margin: 0 auto;\r\n    }\r\n    .ayat-text {\r\n        \r\n    }\r\n    .sura-name {\r\n        text-align: center;\r\n    }\r\n    .line {\r\n    }\r\n.fontQCF_P235 { font-size:36px;font-family:QCF_P235;color:#000;}.ayat11_122 {}\n.ayat11_123 {}\n.line { text-align: center; }.ayat-text {  }.ayat-text:hover { color: #08e8de !important; cursor: pointer; cursor: pointer !important; }.invisible-text { color: white !important;\r\n                            -moz-user-select: none;\r\n                            -webkit-user-select: none;\r\n                            -ms-user-select: none;\r\n                            user-select: none;\r\n                            -o-user-select: none;}.invisible-text:hover { color: white !important;\r\n                            cursor: default !important;\r\n                            -moz-user-select: none;\r\n                            -webkit-user-select: none;\r\n                            -ms-user-select: none;\r\n                            user-select: none;\r\n                            -o-user-select: none;}\r\n</style>\r\n<!-- End inline CSS -->\r\n\r\n<!-- Begin embedded font definitions -->\r\n<style id=\"fonts1\" type=\"text/css\" >\r\n@font-face {font-family: QCF_P235; src: url(\"https://imanakhov.github.io/fonts/qcf_p235.ttf\") format(\"opentype\");}\r\n</style>\r\n<!-- End embedded font definitions -->\r\n\r\n<!-- Begin text definitions (Positioned/styled in CSS) -->\r\n<div class=\"page\"><div class=\"line\"><span class=\"fontQCF_P235 ayat-text invisible-text sura11 ayat11_122\">ﮏ</span><span class=\"fontQCF_P235 ayat-text sura11 ayat11_123\">ﮐ</span><span class=\"fontQCF_P235 ayat-text sura11 ayat11_123\">ﮑ</span><span class=\"fontQCF_P235 ayat-text sura11 ayat11_123\">ﮒ</span><span class=\"fontQCF_P235 ayat-text sura11 ayat11_123\">ﮓ</span><span class=\"fontQCF_P235 ayat-text sura11 ayat11_123\">ﮔ</span><span class=\"fontQCF_P235 ayat-text sura11 ayat11_123\">ﮕ</span><span class=\"fontQCF_P235 ayat-text sura11 ayat11_123\">ﮖ</span><span class=\"fontQCF_P235 ayat-text sura11 ayat11_123\">ﮗ</span></div><div class=\"line\"><span class=\"fontQCF_P235 ayat-text sura11 ayat11_123\">ﮘ</span><span class=\"fontQCF_P235 ayat-text sura11 ayat11_123\">ﮙ</span><span class=\"fontQCF_P235 ayat-text sura11 ayat11_123\">ﮚ</span><span class=\"fontQCF_P235 ayat-text sura11 ayat11_123\">ﮛ</span><span class=\"fontQCF_P235 ayat-text sura11 ayat11_123\">ﮜ</span><span class=\"fontQCF_P235 ayat-text sura11 ayat11_123\">ﮝ</span><span class=\"fontQCF_P235 ayat-text sura11 ayat11_123\">ﮞ</span><span class=\"fontQCF_P235 ayat-text sura11 ayat11_123\">ﮟ</span><span class=\"fontQCF_P235 ayat-text sura11 ayat11_123\">ﮠ</span><span class=\"fontQCF_P235 ayat-text sura11 ayat11_123\">ﮡ</span></div></div>\r\n<!-- End text definitions -->\r\n</div>\r\n</body>\r\n</html>\r\n"},{"page":235,"sura":12,"ayat":1,"html":"<!DOCTYPE html >\r\n<html lang=\"en\">\r\n<head>\r\n<meta http-equiv=\"X-UA-Compatible\" content=\"IE=Edge\" />\r\n<meta charset=\"utf-8\" />\r\n</head>\r\n\r\n<body style=\"\">\r\n<div class=\"quran-container\">\r\n<!-- Begin shared CSS values -->\r\n<style id=\"classes\" type=\"text/css\" >\r\n    .quran-container {\r\n        width: 520px;\r\n        text-align: right;\r\n        padding: 10px;\r\n        margin: 0 auto;\r\n    }\r\n    .ayat-text {\r\n        \r\n    }\r\n    .sura-name {\r\n        text-align: center;\r\n    }\r\n    .line {\r\n    }\r\n.fontQCF_P235 { font-size:36px;font-family:QCF_P235;color:#000;}.ayat12_1 {}\n.ayat12_2 {}\n.line { text-align: center; }.ayat-text {  }.ayat-text:hover { color: #08e8de !important; cursor: pointer; cursor: pointer !important; }.invisible-text { color: white !important;\r\n                            -moz-user-select: none;\r\n                            -webkit-user-select: none;\r\n                            -ms-user-select: none;\r\n                            user-select: none;\r\n                            -o-user-select: none;}.invisible-text:hover { color: white !important;\r\n                            cursor: default !important;\r\n                            -moz-user-select: none;\r\n                            -webkit-user-select: none;\r\n                            -ms-user-select: none;\r\n                            user-select: none;\r\n                            -o-user-select: none;}\r\n</style>\r\n<!-- End inline CSS -->\r\n\r\n<!-- Begin embedded font definitions -->\r\n<style id=\"fonts1\" type=\"text/css\" >\r\n@font-face {font-family: QCF_P235; src: url(\"https://imanakhov.github.io/fonts/qcf_p235.ttf\") format(\"opentype\");}\r\n</style>\r\n<!-- End embedded font definitions -->\r\n\r\n<!-- Begin text definitions (Positioned/styled in CSS) -->\r\n<div class=\"page\"><div class=\"line\"><span class=\"fontQCF_P235 ayat-text sura12 ayat12_1\">ﮢ</span><span class=\"fontQCF_P235 ayat-text sura12 ayat12_1\">ﮣ</span><span class=\"fontQCF_P235 ayat-text sura12 ayat12_1\">ﮤ</span><span class=\"fontQCF_P235 ayat-text sura12 ayat12_1\">ﮥ</span><span class=\"fontQCF_P235 ayat-text sura12 ayat12_1\">ﮦ</span><span class=\"fontQCF_P235 ayat-text sura12 ayat12_1\">ﮧ</span><span class=\"fontQCF_P235 ayat-text sura12 ayat12_1\">ﮨ</span><span class=\"fontQCF_P235 ayat-text invisible-text sura12 ayat12_2\">ﮩ</span><span class=\"fontQCF_P235 ayat-text invisible-text sura12 ayat12_2\">ﮪ</span><span class=\"fontQCF_P235 ayat-text invisible-text sura12 ayat12_2\">ﮫ</span><span class=\"fontQCF_P235 ayat-text invisible-text sura12 ayat12_2\">ﮬ</span></div></div>\r\n<!-- End text definitions -->\r\n</div>\r\n</body>\r\n</html>\r\n"},{"page":235,"sura":12,"ayat":2,"html":"<!DOCTYPE html >\r\n<html lang=\"en\">\r\n<head>\r\n<meta http-equiv=\"X-UA-Compatible\" content=\"IE=Edge\" />\r\n<meta charset=\"utf-8\" />\r\n</head>\r\n\r\n<body style=\"\">\r\n<div class=\"quran-container\">\r\n<!-- Begin shared CSS values -->\r\n<style id=\"classes\" type=\"text/css\" >\r\n    .quran-container {\r\n        width: 520px;\r\n        text-align: right;\r\n        padding: 10px;\r\n        margin: 0 auto;\r\n    }\r\n    .ayat-text {\r\n        \r\n    }\r\n    .sura-name {\r\n        text-align: center;\r\n    }\r\n    .line {\r\n    }\r\n.fontQCF_P235 { font-size:36px;font-family:QCF_P235;color:#000;}.ayat12_1 {}\n.ayat12_2 {}\n.ayat12_3 {}\n.line { text-align: center; }.ayat-text {  }.ayat-text:hover { color: #08e8de !important; cursor: pointer; cursor: pointer !important; }.invisible-text { color: white !important;\r\n                            -moz-user-select: none;\r\n                            -webkit-user-select: none;\r\n                            -ms-user-select: none;\r\n                            user-select: none;\r\n                            -o-user-select: none;}.invisible-text:hover { color: white !important;\r\n                            cursor: default !important;\r\n                            -moz-user-select: none;\r\n                            -webkit-user-select: none;\r\n                            -ms-user-select: none;\r\n                            user-select: none;\r\n                            -o-user-select: none;}\r\n</style>\r\n<!-- End inline CSS -->\r\n\r\n<!-- Begin embedded font definitions -->\r\n<style id=\"fonts1\" type=\"text/css\" >\r\n@font-face {font-family: QCF_P235; src: url(\"https://imanakhov.github.io/fonts/qcf_p235.ttf\") format(\"opentype\");}\r\n</style>\r\n<!-- End embedded font definitions -->\r\n\r\n<!-- Begin text definitions (Positioned/styled in CSS) -->\r\n<div class=\"page\"><div class=\"line\"><span class=\"fontQCF_P235 ayat-text invisible-text sura12 ayat12_1\">ﮢ</span><span class=\"fontQCF_P235 ayat-text invisible-text sura12 ayat12_1\">ﮣ</span><span class=\"fontQCF_P235 ayat-text invisible-text sura12 ayat12_1\">ﮤ</span><span class=\"fontQCF_P235 ayat-text invisible-text sura12 ayat12_1\">ﮥ</span><span class=\"fontQCF_P235 ayat-text invisible-text sura12 ayat12_1\">ﮦ</span><span class=\"fontQCF_P235 ayat-text invisible-text sura12 ayat12_1\">ﮧ</span><span class=\"fontQCF_P235 ayat-text invisible-text sura12 ayat12_1\">ﮨ</span><span class=\"fontQCF_P235 ayat-text sura12 ayat12_2\">ﮩ</span><span class=\"fontQCF_P235 ayat-text sura12 ayat12_2\">ﮪ</span><span class=\"fontQCF_P235 ayat-text sura12 ayat12_2\">ﮫ</span><span class=\"fontQCF_P235 ayat-text sura12 ayat12_2\">ﮬ</span></div><div class=\"line\"><span class=\"fontQCF_P235 ayat-text sura12 ayat12_2\">ﮭ</span><span class=\"fontQCF_P235 ayat-text sura12 ayat12_2\">ﮮ</span><span class=\"fontQCF_P235 ayat-text sura12 ayat12_2\">ﮯ</span><span class=\"fontQCF_P235 ayat-text invisible-text sura12 ayat12_3\">ﮰ</span><span class=\"fontQCF_P235 ayat-text invisible-text sura12 ayat12_3\">ﮱ</span><span class=\"fontQCF_P235 ayat-text invisible-text sura12 ayat12_3\">ﯓ</span><span class=\"fontQCF_P235 ayat-text invisible-text sura12 ayat12_3\">ﯔ</span><span class=\"fontQCF_P235 ayat-text invisible-text sura12 ayat12_3\">ﯕ</span></div></div>\r\n<!-- End text definitions -->\r\n</div>\r\n</body>\r\n</html>\r\n"},{"page":235,"sura":12,"ayat":3,"html":"<!DOCTYPE html >\r\n<html lang=\"en\">\r\n<head>\r\n<meta http-equiv=\"X-UA-Compatible\" content=\"IE=Edge\" />\r\n<meta charset=\"utf-8\" />\r\n</head>\r\n\r\n<body style=\"\">\r\n<div class=\"quran-container\">\r\n<!-- Begin shared CSS values -->\r\n<style id=\"classes\" type=\"text/css\" >\r\n    .quran-container {\r\n        width: 520px;\r\n        text-align: right;\r\n        padding: 10px;\r\n        margin: 0 auto;\r\n    }\r\n    .ayat-text {\r\n        \r\n    }\r\n    .sura-name {\r\n        text-align: center;\r\n    }\r\n    .line {\r\n    }\r\n.fontQCF_P235 { font-size:36px;font-family:QCF_P235;color:#000;}.ayat12_2 {}\n.ayat12_3 {}\n.ayat12_4 {}\n.line { text-align: center; }.ayat-text {  }.ayat-text:hover { color: #08e8de !important; cursor: pointer; cursor: pointer !important; }.invisible-text { color: white !important;\r\n                            -moz-user-select: none;\r\n                            -webkit-user-select: none;\r\n                            -ms-user-select: none;\r\n                            user-select: none;\r\n                            -o-user-select: none;}.invisible-text:hover { color: white !important;\r\n                            cursor: default !important;\r\n                            -moz-user-select: none;\r\n                            -webkit-user-select: none;\r\n                            -ms-user-select: none;\r\n                            user-select: none;\r\n                            -o-user-select: none;}\r\n</style>\r\n<!-- End inline CSS -->\r\n\r\n<!-- Begin embedded font definitions -->\r\n<style id=\"fonts1\" type=\"text/css\" >\r\n@font-face {font-family: QCF_P235; src: url(\"https://imanakhov.github.io/fonts/qcf_p235.ttf\") format(\"opentype\");}\r\n</style>\r\n<!-- End embedded font definitions -->\r\n\r\n<!-- Begin text definitions (Positioned/styled in CSS) -->\r\n<div class=\"page\"><div class=\"line\"><span class=\"fontQCF_P235 ayat-text invisible-text sura12 ayat12_2\">ﮭ</span><span class=\"fontQCF_P235 ayat-text invisible-text sura12 ayat12_2\">ﮮ</span><span class=\"fontQCF_P235 ayat-text invisible-text sura12 ayat12_2\">ﮯ</span><span class=\"fontQCF_P235 ayat-text sura12 ayat12_3\">ﮰ</span><span class=\"fontQCF_P235 ayat-text sura12 ayat12_3\">ﮱ</span><span class=\"fontQCF_P235 ayat-text sura12 ayat12_3\">ﯓ</span><span class=\"fontQCF_P235 ayat-text sura12 ayat12_3\">ﯔ</span><span class=\"fontQCF_P235 ayat-text sura12 ayat12_3\">ﯕ</span></div><div class=\"line\"><span class=\"fontQCF_P235 ayat-text sura12 ayat12_3\">ﯖ</span><span class=\"fontQCF_P235 ayat-text sura12 ayat12_3\">ﯗ</span><span class=\"fontQCF_P235 ayat-text sura12 ayat12_3\">ﯘ</span><span class=\"fontQCF_P235 ayat-text sura12 ayat12_3\">ﯙ</span><span class=\"fontQCF_P235 ayat-text sura12 ayat12_3\">ﯚ</span><span class=\"fontQCF_P235 ayat-text sura12 ayat12_3\">ﯛ</span><span class=\"fontQCF_P235 ayat-text sura12 ayat12_3\">ﯜ</span><span class=\"fontQCF_P235 ayat-text sura12 ayat12_3\">ﯝ</span><span class=\"fontQCF_P235 ayat-text sura12 ayat12_3\">ﯞ</span></div><div class=\"line\"><span class=\"fontQCF_P235 ayat-text sura12 ayat12_3\">ﯟ</span><span class=\"fontQCF_P235 ayat-text sura12 ayat12_3\">ﯠ</span><span class=\"fontQCF_P235 ayat-text sura12 ayat12_3\">ﯡ</span><span class=\"fontQCF_P235 ayat-text invisible-text sura12 ayat12_4\">ﯢ</span><span class=\"fontQCF_P235 ayat-text invisible-text sura12 ayat12_4\">ﯣ</span><span class=\"fontQCF_P235 ayat-text invisible-text sura12 ayat12_4\">ﯤ</span><span class=\"fontQCF_P235 ayat-text invisible-text sura12 ayat12_4\">ﯥ</span><span class=\"fontQCF_P235 ayat-text invisible-text sura12 ayat12_4\">ﯦ</span><span class=\"fontQCF_P235 ayat-text invisible-text sura12 ayat12_4\">ﯧ</span><span class=\"fontQCF_P235 ayat-text invisible-text sura12 ayat12_4\">ﯨ</span></div></div>\r\n<!-- End text definitions -->\r\n</div>\r\n</body>\r\n</html>\r\n"},{"page":235,"sura":12,"ayat":4,"html":"<!DOCTYPE html >\r\n<html lang=\"en\">\r\n<head>\r\n<meta http-equiv=\"X-UA-Compatible\" content=\"IE=Edge\" />\r\n<meta charset=\"utf-8\" />\r\n</head>\r\n\r\n<body style=\"\">\r\n<div class=\"quran-container\">\r\n<!-- Begin shared CSS values -->\r\n<style id=\"classes\" type=\"text/css\" >\r\n    .quran-container {\r\n        width: 520px;\r\n        text-align: right;\r\n        padding: 10px;\r\n        margin: 0 auto;\r\n    }\r\n    .ayat-text {\r\n        \r\n    }\r\n    .sura-name {\r\n        text-align: center;\r\n    }\r\n    .line {\r\n    }\r\n.fontQCF_P235 { font-size:36px;font-family:QCF_P235;color:#000;}.ayat12_3 {}\n.ayat12_4 {}\n.line { text-align: center; }.ayat-text {  }.ayat-text:hover { color: #08e8de !important; cursor: pointer; cursor: pointer !important; }.invisible-text { color: white !important;\r\n                            -moz-user-select: none;\r\n                            -webkit-user-select: none;\r\n                            -ms-user-select: none;\r\n                            user-select: none;\r\n                            -o-user-select: none;}.invisible-text:hover { color: white !important;\r\n                            cursor: default !important;\r\n                            -moz-user-select: none;\r\n                            -webkit-user-select: none;\r\n                            -ms-user-select: none;\r\n                            user-select: none;\r\n                            -o-user-select: none;}\r\n</style>\r\n<!-- End inline CSS -->\r\n\r\n<!-- Begin embedded font definitions -->\r\n<style id=\"fonts1\" type=\"text/css\" >\r\n@font-face {font-family: QCF_P235; src: url(\"https://imanakhov.github.io/fonts/qcf_p235.ttf\") format(\"opentype\");}\r\n</style>\r\n<!-- End embedded font definitions -->\r\n\r\n<!-- Begin text definitions (Positioned/styled in CSS) -->\r\n<div class=\"page\"><div class=\"line\"><span class=\"fontQCF_P235 ayat-text invisible-text sura12 ayat12_3\">ﯟ</span><span class=\"fontQCF_P235 ayat-text invisible-text sura12 ayat12_3\">ﯠ</span><span class=\"fontQCF_P235 ayat-text invisible-text sura12 ayat12_3\">ﯡ</span><span class=\"fontQCF_P235 ayat-text sura12 ayat12_4\">ﯢ</span><span class=\"fontQCF_P235 ayat-text sura12 ayat12_4\">ﯣ</span><span class=\"fontQCF_P235 ayat-text sura12 ayat12_4\">ﯤ</span><span class=\"fontQCF_P235 ayat-text sura12 ayat12_4\">ﯥ</span><span class=\"fontQCF_P235 ayat-text sura12 ayat12_4\">ﯦ</span><span class=\"fontQCF_P235 ayat-text sura12 ayat12_4\">ﯧ</span><span class=\"fontQCF_P235 ayat-text sura12 ayat12_4\">ﯨ</span></div><div class=\"line\"><span class=\"fontQCF_P235 ayat-text sura12 ayat12_4\">ﯩ</span><span class=\"fontQCF_P235 ayat-text sura12 ayat12_4\">ﯪ</span><span class=\"fontQCF_P235 ayat-text sura12 ayat12_4\">ﯫ</span><span class=\"fontQCF_P235 ayat-text sura12 ayat12_4\">ﯬ</span><span class=\"fontQCF_P235 ayat-text sura12 ayat12_4\">ﯭ</span><span class=\"fontQCF_P235 ayat-text sura12 ayat12_4\">ﯮ</span><span class=\"fontQCF_P235 ayat-text sura12 ayat12_4\">ﯯ</span><span class=\"fontQCF_P235 ayat-text sura12 ayat12_4\">ﯰ</span><span class=\"fontQCF_P235 ayat-text sura12 ayat12_4\">ﯱ</span></div></div>\r\n<!-- End text definitions -->\r\n</div>\r\n</body>\r\n</html>\r\n"}]